infraflow/__init__.py
infraflow/cdk/__init__.py
infraflow/cdk/_step_functions/__init__.py
infraflow/cdk/_step_functions/core.py
infraflow/cdk/_step_functions/patterns.py
infraflow/cdk/api_gateway.py
infraflow/cdk/app_patterns/express_default_dlq_processor.py
infraflow/cdk/app_patterns/standard.py
infraflow/cdk/arns.py
infraflow/cdk/core/__init__.py
infraflow/cdk/core/component_service.py
infraflow/cdk/core/construct.py
infraflow/cdk/core/environment.py
infraflow/cdk/core/service_stage.py
infraflow/cdk/core/utils.py
infraflow/cdk/docker.py
infraflow/cdk/events.py
infraflow/cdk/iam/__init__.py
infraflow/cdk/iam/_actions.py
infraflow/cdk/iam/action_groups.py
infraflow/cdk/iam/actions
infraflow/cdk/iam/base.py
infraflow/cdk/instrumentation/__init__.py
infraflow/cdk/instrumentation/alarms.py
infraflow/cdk/instrumentation/docker.py
infraflow/cdk/instrumentation/lambdas.py
infraflow/cdk/instrumentation/metrics.py
infraflow/cdk/instrumentation/queues.py
infraflow/cdk/lambdas.py
infraflow/cdk/queue.py
infraflow/cdk/sg/__init__.py
infraflow/cdk/sg/patterns.py
infraflow/cdk/sg/ports.py
infraflow/cdk/sg/tier_maps.py
infraflow/priv_utils/__init__.py
infraflow/util.py
py_infraflow_cdk-0.1.9.9.1.6.dist-info/METADATA
py_infraflow_cdk-0.1.9.9.1.6.dist-info/WHEEL
py_infraflow_cdk-0.1.9.9.1.6.dist-info/RECORD
